schorle/__init__.py
schorle/_version.py
schorle/app.py
schorle/attrs.py
schorle/component.py
schorle/document.py
schorle/element.py
schorle/events.py
schorle/headers.py
schorle/icon.py
schorle/prototypes.py
schorle/reactive.py
schorle/rendering_context.py
schorle/session.py
schorle/tags.py
schorle/text.py
schorle/theme.py
schorle/types.py
schorle/utils.py
schorle/assets/static/favicon.svg
schorle/scripts/load_css_deps.py
schorle/assets/dist/.gitkeep
schorle/assets/dist/daisyui.min.css
schorle/assets/dist/daisyui.min.css.br
schorle/assets/dist/tailwind.min.js
schorle/assets/dist/tailwind.min.js.br
schorle/assets/js/index.js
schorle/assets/js/index.min.js
schorle/assets/js/index.min.js.br
schorle/assets/js/workers/mainWorker.js
schorle-0.0.25.dist-info/METADATA
schorle-0.0.25.dist-info/WHEEL
schorle-0.0.25.dist-info/licenses/LICENSE.md
schorle-0.0.25.dist-info/RECORD
