Metadata-Version: 2.3
Name: schorle
Version: 0.0.25
Summary: Server-driven UI kit for Python with async support
Project-URL: Documentation, https://github.com/renardeinside/schorle#readme
Project-URL: Issues, https://github.com/renardeinside/schorle/issues
Project-URL: Source, https://github.com/renardeinside/schorle
Author-email: renardeinside <polarpersonal@gmail.com>
License-Expression: MIT
License-File: LICENSE.md
Keywords: async,python,server-driven-ui,ui
Classifier: Development Status :: 4 - Beta
Classifier: Programming Language :: Python
Classifier: Programming Language :: Python :: 3.7
Classifier: Programming Language :: Python :: 3.8
Classifier: Programming Language :: Python :: 3.9
Classifier: Programming Language :: Python :: 3.10
Classifier: Programming Language :: Python :: 3.11
Classifier: Programming Language :: Python :: Implementation :: CPython
Requires-Python: >=3.7
Requires-Dist: bidict
Requires-Dist: fastapi
Requires-Dist: loguru
Requires-Dist: lxml
Requires-Dist: python-multipart
Requires-Dist: uvicorn[standard]
